[
    {
        "pages": [
            {
                "page": 1,
                "text": "      INSTITUTO FEDERAL DE EDUCACAO, CIENCIAE TECNOLOGIA DE SAO PAULOMINISTERIO DA EDUCACAO\n            PORTARIA BTV.0161/2018, DE 12 DE DEZEMBRO DE 2018.\n                                                               Substituicaonoperiodo de ferias\n                                                               da CDI\n        0 DIRETOR GERAL DO CAMPUS BOITUVA, DO INSTITUTO FEDERAL\nDEEDUCACAO, CIENCIAE TECNOLOGIADE SAo PAULOno uSO de suas\natribuicoes legais delegadas pela Portaria n\" 3.903. de 04 de novembro de 2015,e 0que\nconsta n0protocolo n\" 23431.001100.2018-16,\n        RESOLVE:\n        DESIGNAR         servidor FELIPE GOBO BRUNO, ocupante do cargo de Teenico de\nLaboratorio de Informatica, pertencente a0 Quadro Permanente deste IFSP, para substituir\n   Coordenadorade       Apoio      Direcao(FG-02)do Campus   Boituva,noperiodode\n10/01/2019 a 18/01/2019,por motivo de ferias\n                                   BRUNO NOGUEIRA LUZ\n                                                                           Publicado em:",
                "md": "INSTITUTO FEDERAL DE EDUCACAO, CIENCIA E TECNOLOGIA DE SAO PAULO MINISTERIO DA EDUCACAO\n\nPORTARIA BTV.0161/2018, DE 12 DE DEZEMBRO DE 2018.\n\nSubstituicao no periodo de ferias da CDI\n\nO DIRETOR GERAL DO CAMPUS BOITUVA, DO INSTITUTO FEDERAL DE EDUCACAO, CIENCIA E TECNOLOGIA DE SAO PAULO no uso de suas atribuicoes legais delegadas pela Portaria n° 3.903, de 04 de novembro de 2015, e o que consta no protocolo n° 23431.001100.2018-16,\n\nRESOLVE:\n\nDESIGNAR servidor FELIPE GOBO BRUNO, ocupante do cargo de Tecnico de Laboratorio de Informatica, pertencente ao Quadro Permanente deste IFSP, para substituir Coordenadora de Apoio a Direcao (FG-02) do Campus Boituva, no periodo de 10/01/2019 a 18/01/2019, por motivo de ferias\n\nBRUNO NOGUEIRA LUZ\n\nPublicado em:",
                "images": [
                    {
                        "name": "img_p0_1.png",
                        "height": 1584,
                        "width": 1224
                    }
                ],
                "items": [
                    {
                        "type": "text",
                        "value": "INSTITUTO FEDERAL DE EDUCACAO, CIENCIA E TECNOLOGIA DE SAO PAULO MINISTERIO DA EDUCACAO\n\nPORTARIA BTV.0161/2018, DE 12 DE DEZEMBRO DE 2018.\n\nSubstituicao no periodo de ferias da CDI\n\nO DIRETOR GERAL DO CAMPUS BOITUVA, DO INSTITUTO FEDERAL DE EDUCACAO, CIENCIA E TECNOLOGIA DE SAO PAULO no uso de suas atribuicoes legais delegadas pela Portaria n° 3.903, de 04 de novembro de 2015, e o que consta no protocolo n° 23431.001100.2018-16,\n\nRESOLVE:\n\nDESIGNAR servidor FELIPE GOBO BRUNO, ocupante do cargo de Tecnico de Laboratorio de Informatica, pertencente ao Quadro Permanente deste IFSP, para substituir Coordenadora de Apoio a Direcao (FG-02) do Campus Boituva, no periodo de 10/01/2019 a 18/01/2019, por motivo de ferias\n\nBRUNO NOGUEIRA LUZ\n\nPublicado em:",
                        "md": "INSTITUTO FEDERAL DE EDUCACAO, CIENCIA E TECNOLOGIA DE SAO PAULO MINISTERIO DA EDUCACAO\n\nPORTARIA BTV.0161/2018, DE 12 DE DEZEMBRO DE 2018.\n\nSubstituicao no periodo de ferias da CDI\n\nO DIRETOR GERAL DO CAMPUS BOITUVA, DO INSTITUTO FEDERAL DE EDUCACAO, CIENCIA E TECNOLOGIA DE SAO PAULO no uso de suas atribuicoes legais delegadas pela Portaria n° 3.903, de 04 de novembro de 2015, e o que consta no protocolo n° 23431.001100.2018-16,\n\nRESOLVE:\n\nDESIGNAR servidor FELIPE GOBO BRUNO, ocupante do cargo de Tecnico de Laboratorio de Informatica, pertencente ao Quadro Permanente deste IFSP, para substituir Coordenadora de Apoio a Direcao (FG-02) do Campus Boituva, no periodo de 10/01/2019 a 18/01/2019, por motivo de ferias\n\nBRUNO NOGUEIRA LUZ\n\nPublicado em:"
                    }
                ]
            }
        ],
        "job_metadata": {
            "credits_used": 600.0,
            "credits_max": 1000,
            "job_credits_usage": 1,
            "job_pages": 1,
            "job_is_cache_hit": false
        },
        "job_id": "7e35e2ca-8dfe-4f75-916e-76ee5dd18de2",
        "file_path": "/content/ia024-projeto-rag/0-downloaded-files/2-boituva/portarias/2018/12 - Dezembro/Dez_Port_0161_Substituição da CDI por motivo de férias_BTV.pdf"
    }
]