[
    {
        "pages": [
            {
                "page": 1,
                "text": "      JF1\n      V9#    1   18110L5    715\n   1  1$\n       882V      K\n                 113     11 V3\n       181\n        81        Hl11   V\n                          3\n                         0  11\n         7       1\n       FH3      #1187    83 1\n9       3         31\n       W1 &      0    8",
                "md": "|JF1|\n|---|\n|V9#|1|18110L5|715|\n|1|1$|\n|882V|K|\n|113|11 V3|\n|181|\n|81|Hl11|V|\n|3|0 11|\n|7|1|\n|FH3|#1187|83 1|\n|9|3|31|\n|W1 &|0|8|",
                "images": [
                    {
                        "name": "img_p0_1.png",
                        "height": 1684,
                        "width": 1191
                    }
                ],
                "items": [
                    {
                        "type": "table",
                        "rows": [
                            [
                                "JF1"
                            ],
                            [
                                "V9#",
                                "1",
                                "18110L5",
                                "715"
                            ],
                            [
                                "1",
                                "1$"
                            ],
                            [
                                "882V",
                                "K"
                            ],
                            [
                                "113",
                                "11 V3"
                            ],
                            [
                                "181"
                            ],
                            [
                                "81",
                                "Hl11",
                                "V"
                            ],
                            [
                                "3",
                                "0 11"
                            ],
                            [
                                "7",
                                "1"
                            ],
                            [
                                "FH3",
                                "#1187",
                                "83 1"
                            ],
                            [
                                "9",
                                "3",
                                "31"
                            ],
                            [
                                "W1 &",
                                "0",
                                "8"
                            ]
                        ],
                        "md": "|JF1|\n|---|\n|V9#|1|18110L5|715|\n|1|1$|\n|882V|K|\n|113|11 V3|\n|181|\n|81|Hl11|V|\n|3|0 11|\n|7|1|\n|FH3|#1187|83 1|\n|9|3|31|\n|W1 &|0|8|",
                        "isPerfectTable": false,
                        "csv": "\"JF1\"\n\"V9#\",\"1\",\"18110L5\",\"715\"\n\"1\",\"1$\"\n\"882V\",\"K\"\n\"113\",\"11 V3\"\n\"181\"\n\"81\",\"Hl11\",\"V\"\n\"3\",\"0 11\"\n\"7\",\"1\"\n\"FH3\",\"#1187\",\"83 1\"\n\"9\",\"3\",\"31\"\n\"W1 &\",\"0\",\"8\""
                    }
                ]
            }
        ],
        "job_metadata": {
            "credits_used": 150.0,
            "credits_max": 1000,
            "job_credits_usage": 1,
            "job_pages": 1,
            "job_is_cache_hit": false
        },
        "job_id": "e0ebc409-1c81-49e6-b4da-e84f238a204a",
        "file_path": "/content/ia024-projeto-rag/0-downloaded-files/2-boituva/portarias/2015/10 - Outubro/Out_Port_0090_Substituição de período de férias CGP.pdf"
    }
]