[
    {
        "pages": [
            {
                "page": 1,
                "text": "                                    MINISTÉRIO DA EDUCAÇÃO\n      INSTITUTO FEDERAL DE EDUCAÇÃO, CIÊNCIA E TECNOLOGIA DE SÃO PAULO\n\n\n                  PORTARIA BTV.0029/2021, DE 04 DE MAIO DE 2021.\n\n\n                                                                Revogar            as         Portarias\n                                                                BTV.0028/2020 e BTV.0037/2020\n                                                                e Constituir o grupo de trabalho\n                                                                para Acessibilidade digital aos\n                                                                Docentes            e          Técnicos\n                                                                Administrativos         para      ações\n                                                                durante e pós pandemia, do\n                                                                Câmpus Boituva, para o ano de\n                                                                2021.\n\n\n        O DIRETOR-GERAL DO CÂMPUS BOITUVA, DO INSTITUTO FEDERAL\nDE EDUCAÇÃO, CIÊNCIA E TECNOLOGIA DE SÃO PAULO, no uso de suas\natribuições legais delegadas pela Portaria nº 3.903, de 04 de novembro de 2015,\n\n\n        RESOLVE\n\n\n        Art. 1º - REVOGAR as Portarias BTV.0028/2020 de 01 de junho de 2020 e\nBTV.0037/2020 de 04 de junho de 2020.\n\n\n        Art. 2º - CONSTITUIR, o grupo de trabalho para Acessibilidade digital aos\nDocentes e Técnicos Administrativos para ações durante e pós pandemia, do Câmpus\nBoituva, para o ano de 2021.\n\n\n        Art. 3º - ATRIBUIÇÕES DO GRUPO: responsável pelo estudo e elaboração de\nproposta com a finalidade de tornar viável o acesso de docentes e técnicos administrativos\nàs MEAOs e atividades remotas durante e após a pandemia. Este GT terá apoio de\nmembros do CTI para facilitar o uso de tecnologias e ferramentas como por exemplo a\nVPN, Classroom, Microsoft Teams, etc.\n\n\n        Art. 4º - DESIGNAR, os servidores e discente abaixo relacionados para, sob a\ncoordenação do primeiro, comporem o grupo de trabalho supracitado:\n                 Helton Moreira de Almeida\n                 Diego Saturnino Araujo da Silva\n                 Felipe Gobo Bruno\n                 Jennifer Vasconcelos de Carvalho - discente\n                 Marcelo Figueiredo Polido\n                 Marcelo Monteiro\n\n\n                                                                                 Publicado em:\n\n\n                                                                               ____/____/____",
                "md": "# MINISTÉRIO DA EDUCAÇÃO INSTITUTO FEDERAL DE EDUCAÇÃO, CIÊNCIA E TECNOLOGIA DE SÃO PAULO\n\nPORTARIA BTV.0029/2021, DE 04 DE MAIO DE 2021.\n\nRevogar as Portarias BTV.0028/2020 e BTV.0037/2020 e Constituir o grupo de trabalho para Acessibilidade digital aos Docentes e Técnicos Administrativos para ações durante e pós pandemia, do Câmpus Boituva, para o ano de 2021.\n\nO DIRETOR-GERAL DO CÂMPUS BOITUVA, DO INSTITUTO FEDERAL DE EDUCAÇÃO CIÊNCIA E TECNOLOGIA DE SÃO PAULO, no uso de suas atribuições legais delegadas pela Portaria nº 3.903, de 04 de novembro de 2015,\n\nRESOLVE\n\nArt. 1º - REVOGAR as Portarias BTV.0028/2020 de 01 de junho de 2020 e BTV.0037/2020 de 04 de junho de 2020.\n\nArt. 2º - CONSTITUIR, o grupo de trabalho para Acessibilidade digital aos Docentes e Técnicos Administrativos para ações durante e pós pandemia, do Câmpus Boituva, para o ano de 2021.\n\nArt. 3º - ATRIBUIÇÕES DO GRUPO: responsável pelo estudo e elaboração de proposta com a finalidade de tornar viável o acesso de docentes e técnicos administrativos às MEAOs e atividades remotas durante e após a pandemia. Este GT terá apoio de membros do CTI para facilitar o uso de tecnologias e ferramentas como por exemplo a VPN, Classroom, Microsoft Teams, etc.\n\nArt. 4º - DESIGNAR, os servidores e discente abaixo relacionados para, sob a coordenação do primeiro, comporem o grupo de trabalho supracitado:\n\nHelton Moreira de Almeida\nDiego Saturnino Araujo da Silva\nFelipe Gobo Bruno\nJennifer Vasconcelos de Carvalho - discente\nMarcelo Figueiredo Polido\nMarcelo Monteiro\n\nPublicado em: ____/____/____",
                "images": [
                    {
                        "name": "img_p0_1.png",
                        "height": 151,
                        "width": 143
                    }
                ],
                "items": [
                    {
                        "type": "heading",
                        "lvl": 1,
                        "value": "MINISTÉRIO DA EDUCAÇÃO INSTITUTO FEDERAL DE EDUCAÇÃO, CIÊNCIA E TECNOLOGIA DE SÃO PAULO",
                        "md": "# MINISTÉRIO DA EDUCAÇÃO INSTITUTO FEDERAL DE EDUCAÇÃO, CIÊNCIA E TECNOLOGIA DE SÃO PAULO"
                    },
                    {
                        "type": "text",
                        "value": "PORTARIA BTV.0029/2021, DE 04 DE MAIO DE 2021.\n\nRevogar as Portarias BTV.0028/2020 e BTV.0037/2020 e Constituir o grupo de trabalho para Acessibilidade digital aos Docentes e Técnicos Administrativos para ações durante e pós pandemia, do Câmpus Boituva, para o ano de 2021.\n\nO DIRETOR-GERAL DO CÂMPUS BOITUVA, DO INSTITUTO FEDERAL DE EDUCAÇÃO CIÊNCIA E TECNOLOGIA DE SÃO PAULO, no uso de suas atribuições legais delegadas pela Portaria nº 3.903, de 04 de novembro de 2015,\n\nRESOLVE\n\nArt. 1º - REVOGAR as Portarias BTV.0028/2020 de 01 de junho de 2020 e BTV.0037/2020 de 04 de junho de 2020.\n\nArt. 2º - CONSTITUIR, o grupo de trabalho para Acessibilidade digital aos Docentes e Técnicos Administrativos para ações durante e pós pandemia, do Câmpus Boituva, para o ano de 2021.\n\nArt. 3º - ATRIBUIÇÕES DO GRUPO: responsável pelo estudo e elaboração de proposta com a finalidade de tornar viável o acesso de docentes e técnicos administrativos às MEAOs e atividades remotas durante e após a pandemia. Este GT terá apoio de membros do CTI para facilitar o uso de tecnologias e ferramentas como por exemplo a VPN, Classroom, Microsoft Teams, etc.\n\nArt. 4º - DESIGNAR, os servidores e discente abaixo relacionados para, sob a coordenação do primeiro, comporem o grupo de trabalho supracitado:\n\nHelton Moreira de Almeida\nDiego Saturnino Araujo da Silva\nFelipe Gobo Bruno\nJennifer Vasconcelos de Carvalho - discente\nMarcelo Figueiredo Polido\nMarcelo Monteiro\n\nPublicado em: ____/____/____",
                        "md": "PORTARIA BTV.0029/2021, DE 04 DE MAIO DE 2021.\n\nRevogar as Portarias BTV.0028/2020 e BTV.0037/2020 e Constituir o grupo de trabalho para Acessibilidade digital aos Docentes e Técnicos Administrativos para ações durante e pós pandemia, do Câmpus Boituva, para o ano de 2021.\n\nO DIRETOR-GERAL DO CÂMPUS BOITUVA, DO INSTITUTO FEDERAL DE EDUCAÇÃO CIÊNCIA E TECNOLOGIA DE SÃO PAULO, no uso de suas atribuições legais delegadas pela Portaria nº 3.903, de 04 de novembro de 2015,\n\nRESOLVE\n\nArt. 1º - REVOGAR as Portarias BTV.0028/2020 de 01 de junho de 2020 e BTV.0037/2020 de 04 de junho de 2020.\n\nArt. 2º - CONSTITUIR, o grupo de trabalho para Acessibilidade digital aos Docentes e Técnicos Administrativos para ações durante e pós pandemia, do Câmpus Boituva, para o ano de 2021.\n\nArt. 3º - ATRIBUIÇÕES DO GRUPO: responsável pelo estudo e elaboração de proposta com a finalidade de tornar viável o acesso de docentes e técnicos administrativos às MEAOs e atividades remotas durante e após a pandemia. Este GT terá apoio de membros do CTI para facilitar o uso de tecnologias e ferramentas como por exemplo a VPN, Classroom, Microsoft Teams, etc.\n\nArt. 4º - DESIGNAR, os servidores e discente abaixo relacionados para, sob a coordenação do primeiro, comporem o grupo de trabalho supracitado:\n\nHelton Moreira de Almeida\nDiego Saturnino Araujo da Silva\nFelipe Gobo Bruno\nJennifer Vasconcelos de Carvalho - discente\nMarcelo Figueiredo Polido\nMarcelo Monteiro\n\nPublicado em: ____/____/____"
                    }
                ]
            },
            {
                "page": 2,
                "text": "                                     MINISTÉRIO DA EDUCAÇÃO\n      INSTITUTO FEDERAL DE EDUCAÇÃO, CIÊNCIA E TECNOLOGIA DE SÃO PAULO\n\n\n        Art. 5º - Ficará a cargo do Coordenador da Comissão, organizar as reuniões, que\ndeverão ser registradas em ata específica contendo o tema ou pauta da reunião e assinaturas\ndos presentes. Estes registros deverão ser encaminhados, no prazo de 10 (dez) dias, após\ncada reunião, à Direção Geral do Câmpus, devendo também, apresentar relatórios,\nmensalmente, à Direção Geral do Câmpus.\n\n\n        Art. 6º - Os membros da comissão terão 1(uma) hora de dedicação para o\ndesenvolvimento das atividades.\n\n\n        Art. 7º - Convalidar os atos dos membros a partir de 01 de fevereiro de 2021.\n\n\n                          FELIPE AUGUSTO FERREIRA DE ALMEIDA\n\n\n                                                                                    Publicado em:\n\n\n                                                                                   ____/____/____",
                "md": "# MINISTÉRIO DA EDUCAÇÃO INSTITUTO FEDERAL DE EDUCAÇÃO, CIÊNCIA E TECNOLOGIA DE SÃO PAULO\n\nArt. 5º - Ficará a cargo do Coordenador da Comissão, organizar as reuniões, que deverão ser registradas em ata específica contendo o tema ou pauta da reunião e assinaturas dos presentes. Estes registros deverão ser encaminhados, no prazo de 10 (dez) dias, após cada reunião, à Direção Geral do Câmpus, devendo também, apresentar relatórios, mensalmente, à Direção Geral do Câmpus.\n\nArt. 6º - Os membros da comissão terão 1(uma) hora de dedicação para o desenvolvimento das atividades.\n\nArt. 7º - Convalidar os atos dos membros a partir de 01 de fevereiro de 2021.\n\nFELIPE AUGUSTO FERREIRA DE ALMEIDA\n\nPublicado em:\n\n____/____/____",
                "images": [],
                "items": [
                    {
                        "type": "heading",
                        "lvl": 1,
                        "value": "MINISTÉRIO DA EDUCAÇÃO INSTITUTO FEDERAL DE EDUCAÇÃO, CIÊNCIA E TECNOLOGIA DE SÃO PAULO",
                        "md": "# MINISTÉRIO DA EDUCAÇÃO INSTITUTO FEDERAL DE EDUCAÇÃO, CIÊNCIA E TECNOLOGIA DE SÃO PAULO"
                    },
                    {
                        "type": "text",
                        "value": "Art. 5º - Ficará a cargo do Coordenador da Comissão, organizar as reuniões, que deverão ser registradas em ata específica contendo o tema ou pauta da reunião e assinaturas dos presentes. Estes registros deverão ser encaminhados, no prazo de 10 (dez) dias, após cada reunião, à Direção Geral do Câmpus, devendo também, apresentar relatórios, mensalmente, à Direção Geral do Câmpus.\n\nArt. 6º - Os membros da comissão terão 1(uma) hora de dedicação para o desenvolvimento das atividades.\n\nArt. 7º - Convalidar os atos dos membros a partir de 01 de fevereiro de 2021.\n\nFELIPE AUGUSTO FERREIRA DE ALMEIDA\n\nPublicado em:\n\n____/____/____",
                        "md": "Art. 5º - Ficará a cargo do Coordenador da Comissão, organizar as reuniões, que deverão ser registradas em ata específica contendo o tema ou pauta da reunião e assinaturas dos presentes. Estes registros deverão ser encaminhados, no prazo de 10 (dez) dias, após cada reunião, à Direção Geral do Câmpus, devendo também, apresentar relatórios, mensalmente, à Direção Geral do Câmpus.\n\nArt. 6º - Os membros da comissão terão 1(uma) hora de dedicação para o desenvolvimento das atividades.\n\nArt. 7º - Convalidar os atos dos membros a partir de 01 de fevereiro de 2021.\n\nFELIPE AUGUSTO FERREIRA DE ALMEIDA\n\nPublicado em:\n\n____/____/____"
                    }
                ]
            }
        ],
        "job_metadata": {
            "credits_used": 257.0,
            "credits_max": 1000,
            "job_credits_usage": 2,
            "job_pages": 2,
            "job_is_cache_hit": false
        },
        "job_id": "ab270c9d-af29-4f60-acd5-33a36fdce42d",
        "file_path": "/content/ia024-projeto-rag/0-downloaded-files/2-boituva/portarias/2021/05 - Maio/Mai_Port_0029_Grupo de trabalho GT3-Acessibilidade digital aos Docentes e Técnicos Administrativos_BTV.pdf"
    }
]